django_keoh_userprofile-0.0.5.dist-info/METADATA
django_keoh_userprofile-0.0.5.dist-info/RECORD
django_keoh_userprofile-0.0.5.dist-info/WHEEL
django_keoh_userprofile-0.0.5.dist-info/top_level.txt
tests/unit/__init__.py
tests/unit/test_import.py
user_profile/__init__.py
user_profile/admin.py
user_profile/models.py
user_profile/migrations/0001_initial.py
user_profile/migrations/__init__.py
user_profile/static/empty
user_profile/static/css/userprofile.css
user_profile/static/img/default.png
user_profile/static/js/awesome-forms.js
