Metadata-Version: 2.1
Name: django-keoh-userprofile
Version: 0.0.5
Summary: A simple Django app to manage user profiles
Home-page: https://github.com/KeoH/django-keoh-userprofile
Author: Francisco Manzano Magaña
Author-email: keoh77@gmail.com
License: UNKNOWN
Project-URL: Bug Reports, https://github.com/KeoH/django-keoh-userprofile/issues
Project-URL: Source, https://github.com/KeoH/django-keoh-userprofile/
Keywords: profile,django,user
Platform: UNKNOWN
Classifier: Development Status :: 1 - Planning
Classifier: Environment :: Web Environment
Classifier: Framework :: Django
Classifier: Intended Audience :: Developers
Classifier: License :: OSI Approved :: MIT License
Classifier: Operating System :: OS Independent
Classifier: Programming Language :: Python :: 3
Classifier: Programming Language :: Python :: 3.4
Classifier: Programming Language :: Python :: 3.5
Classifier: Programming Language :: Python :: 3.6
Classifier: Programming Language :: Python :: 3.7
Requires-Python: >=3.4
Provides-Extra: test
Provides-Extra: dev
Requires-Dist: pillow
Provides-Extra: dev
Requires-Dist: check-manifest; extra == 'dev'
Provides-Extra: test
Requires-Dist: coverage; extra == 'test'
